{
	"Generated": "2026-05-31T01:44:02.388Z",
	"Mode": "module",
	"DocumentCount": 4,
	"LunrIndex": {
		"version": "2.3.9",
		"fields": [
			"title",
			"module",
			"group",
			"body"
		],
		"fieldVectors": [
			[
				"title/README.md",
				[
					0,
					3.035,
					1,
					3.707
				]
			],
			[
				"module/README.md",
				[
					0,
					1.724,
					1,
					2.106
				]
			],
			[
				"group/README.md",
				[]
			],
			[
				"body/README.md",
				[
					0,
					0.364,
					1,
					0.864,
					2,
					0.182,
					3,
					0.377,
					4,
					0.377,
					5,
					0.17,
					6,
					0.15,
					7,
					0.576,
					8,
					0.15,
					9,
					0.732,
					10,
					0.645,
					11,
					0.15,
					12,
					0.213,
					13,
					0.617,
					14,
					0.732,
					15,
					1.271,
					16,
					0.732,
					17,
					1.271,
					18,
					0.732,
					19,
					0.732,
					20,
					1.271,
					21,
					0.732,
					22,
					1.271,
					23,
					0.732,
					24,
					0.732,
					25,
					0.732,
					26,
					0.377,
					27,
					0.732,
					28,
					0.732,
					29,
					0.509,
					30,
					0.732,
					31,
					1.271,
					32,
					0.377,
					33,
					0.732,
					34,
					0.732,
					35,
					0.17,
					36,
					0.576,
					37,
					0.732,
					38,
					0.732,
					39,
					0.377,
					40,
					0.732,
					41,
					0.732,
					42,
					0.377,
					43,
					0.617,
					44,
					0.377,
					45,
					0.576,
					46,
					0.377,
					47,
					0.645,
					48,
					0.989,
					49,
					0.509,
					50,
					0.732,
					51,
					0.989,
					52,
					0.576,
					53,
					0.989,
					54,
					0.732,
					55,
					0.732,
					56,
					0.22,
					57,
					0.732,
					58,
					0.377,
					59,
					0.377,
					60,
					0.989,
					61,
					0.732,
					62,
					0.732,
					63,
					0.157,
					64,
					1.271,
					65,
					0.15,
					66,
					1.271,
					67,
					0.732,
					68,
					0.377,
					69,
					0.509,
					70,
					0.509,
					71,
					0.509,
					72,
					0.377,
					73,
					0.377,
					74,
					0.617,
					75,
					0.377,
					76,
					0.732,
					77,
					0.377,
					78,
					0.377,
					79,
					0.377,
					80,
					0.377,
					81,
					0.111,
					82,
					0.377,
					83,
					0.989,
					84,
					0.377,
					85,
					0.377,
					86,
					0.182,
					87,
					0.19,
					88,
					0.509,
					89,
					0.509,
					90,
					0.509,
					91,
					0.509,
					92,
					0.509,
					93,
					0.509,
					94,
					0.732,
					95,
					0.111,
					96,
					0.732,
					97,
					0.732,
					98,
					0.732,
					99,
					0.111,
					100,
					0.509,
					101,
					0.732,
					102,
					0.732,
					103,
					0.509,
					104,
					0.377,
					105,
					1.271,
					106,
					0.989,
					107,
					1.271,
					108,
					0.377,
					109,
					0.509,
					110,
					0.15,
					111,
					0.509,
					112,
					0.509,
					113,
					0.989,
					114,
					0.377,
					115,
					0.377,
					116,
					0.377,
					117,
					0.377,
					118,
					0.732,
					119,
					0.732,
					120,
					1.271,
					121,
					0.377,
					122,
					1.271,
					123,
					0.732,
					124,
					0.377,
					125,
					0.377,
					126,
					0.377,
					127,
					0.111,
					128,
					0.989,
					129,
					0.377,
					130,
					0.989,
					131,
					0.377,
					132,
					0.377,
					133,
					0.509,
					134,
					0.377,
					135,
					0.989,
					136,
					0.732,
					137,
					0.732,
					138,
					0.732,
					139,
					0.732,
					140,
					0.732,
					141,
					0.732,
					142,
					0.732,
					143,
					0.732,
					144,
					0.377,
					145,
					0.732,
					146,
					0.732,
					147,
					0.989,
					148,
					0.732,
					149,
					0.732,
					150,
					1.271,
					151,
					1.271,
					152,
					1.271
				]
			],
			[
				"title/_cover.md",
				[
					0,
					3.035,
					1,
					3.707
				]
			],
			[
				"module/_cover.md",
				[
					0,
					1.724,
					1,
					2.106
				]
			],
			[
				"group/_cover.md",
				[]
			],
			[
				"body/_cover.md",
				[
					0,
					0.534,
					1,
					0.839,
					2,
					0.192,
					3,
					0.553,
					4,
					0.553,
					5,
					0.163,
					6,
					0.163,
					7,
					0.553,
					8,
					0.163,
					9,
					1.074,
					10,
					0.648,
					11,
					0.163,
					12,
					0.192,
					13,
					0.553,
					29,
					0.553,
					32,
					0.553,
					35,
					0.163,
					56,
					0.163,
					63,
					0.135,
					65,
					0.163,
					67,
					1.074,
					72,
					0.553,
					75,
					0.553,
					76,
					1.074,
					77,
					0.553,
					78,
					0.553,
					79,
					0.553,
					81,
					0.163,
					85,
					0.553,
					86,
					0.163,
					87,
					0.163,
					95,
					0.163,
					99,
					0.163,
					108,
					0.553,
					127,
					0.163,
					153,
					1.865
				]
			],
			[
				"title/how-it-works.md",
				[
					63,
					1.008
				]
			],
			[
				"module/how-it-works.md",
				[
					0,
					1.724,
					1,
					2.106
				]
			],
			[
				"group/how-it-works.md",
				[]
			],
			[
				"body/how-it-works.md",
				[
					1,
					0.856,
					2,
					0.072,
					5,
					0.109,
					6,
					0.109,
					7,
					0.242,
					8,
					0.16,
					10,
					0.542,
					11,
					0.133,
					12,
					0.213,
					13,
					0.542,
					14,
					0.72,
					16,
					0.72,
					18,
					0.471,
					19,
					0.471,
					21,
					0.471,
					23,
					0.471,
					24,
					0.471,
					25,
					0.471,
					26,
					0.242,
					27,
					0.471,
					28,
					0.471,
					29,
					0.449,
					30,
					0.72,
					32,
					0.449,
					33,
					0.471,
					34,
					0.471,
					35,
					0.149,
					36,
					0.542,
					37,
					0.978,
					38,
					0.471,
					39,
					0.503,
					40,
					0.72,
					41,
					0.471,
					42,
					0.242,
					43,
					0.595,
					44,
					0.542,
					45,
					0.613,
					46,
					0.37,
					47,
					0.669,
					48,
					0.873,
					49,
					0.542,
					50,
					0.471,
					51,
					0.72,
					52,
					0.572,
					54,
					0.471,
					55,
					0.873,
					56,
					0.222,
					57,
					0.873,
					58,
					0.542,
					59,
					0.37,
					60,
					1.111,
					61,
					0.471,
					62,
					0.873,
					63,
					0.123,
					65,
					0.133,
					68,
					0.242,
					69,
					0.503,
					70,
					0.449,
					71,
					0.242,
					72,
					0.242,
					73,
					0.37,
					74,
					0.677,
					75,
					0.37,
					77,
					0.37,
					78,
					0.449,
					79,
					0.449,
					80,
					0.503,
					81,
					0.189,
					82,
					0.542,
					83,
					1.156,
					84,
					0.613,
					85,
					0.542,
					86,
					0.133,
					87,
					0.133,
					88,
					0.242,
					89,
					0.37,
					90,
					0.242,
					91,
					0.242,
					92,
					0.242,
					93,
					0.242,
					94,
					0.471,
					95,
					0.16,
					96,
					0.72,
					97,
					0.72,
					98,
					0.72,
					99,
					0.149,
					100,
					0.503,
					101,
					0.471,
					102,
					0.72,
					103,
					0.37,
					104,
					0.449,
					106,
					0.471,
					108,
					0.449,
					109,
					0.449,
					110,
					0.109,
					111,
					0.242,
					112,
					0.37,
					113,
					0.978,
					114,
					0.37,
					115,
					0.242,
					116,
					0.242,
					117,
					0.242,
					118,
					0.72,
					119,
					0.873,
					121,
					0.542,
					123,
					0.471,
					124,
					0.242,
					125,
					0.242,
					126,
					0.242,
					127,
					0.181,
					129,
					0.242,
					130,
					0.978,
					131,
					0.242,
					132,
					0.242,
					133,
					0.449,
					134,
					0.542,
					136,
					0.471,
					137,
					0.471,
					138,
					0.471,
					139,
					0.471,
					140,
					0.873,
					141,
					0.471,
					144,
					0.503,
					145,
					0.471,
					146,
					0.471,
					147,
					0.72,
					148,
					0.471,
					149,
					0.471,
					154,
					0.818,
					155,
					0.818,
					156,
					0.818,
					157,
					1.25,
					158,
					0.818,
					159,
					0.818,
					160,
					0.818,
					161,
					1.517,
					162,
					0.818,
					163,
					0.818,
					164,
					1.699,
					165,
					0.818,
					166,
					0.818,
					167,
					0.818,
					168,
					1.25,
					169,
					1.25,
					170,
					0.818,
					171,
					0.818,
					172,
					0.818,
					173,
					0.818,
					174,
					0.818,
					175,
					1.699,
					176,
					0.818,
					177,
					0.818,
					178,
					1.25,
					179,
					0.818,
					180,
					0.818,
					181,
					1.25,
					182,
					0.818,
					183,
					0.471,
					184,
					1.699,
					185,
					0.818,
					186,
					1.25,
					187,
					0.818,
					188,
					1.25,
					189,
					0.818,
					190,
					1.929,
					191,
					0.72,
					192,
					0.818,
					193,
					0.818,
					194,
					1.25,
					195,
					0.978,
					196,
					1.517,
					197,
					1.111,
					198,
					0.818,
					199,
					0.818,
					200,
					0.818,
					201,
					0.818,
					202,
					0.818,
					203,
					1.699,
					204,
					0.818,
					205,
					0.818,
					206,
					1.25,
					207,
					0.818,
					208,
					0.471,
					209,
					0.818,
					210,
					0.818,
					211,
					0.873,
					212,
					0.818,
					213,
					0.818,
					214,
					0.818,
					215,
					0.818,
					216,
					1.25,
					217,
					1.25,
					218,
					0.72,
					219,
					1.517,
					220,
					0.818,
					221,
					0.471,
					222,
					0.818,
					223,
					1.25,
					224,
					0.818,
					225,
					0.818,
					226,
					0.818,
					227,
					0.818,
					228,
					0.818,
					229,
					0.818,
					230,
					1.25,
					231,
					0.818,
					232,
					0.818,
					233,
					0.873,
					234,
					0.818,
					235,
					1.25,
					236,
					0.818,
					237,
					0.818,
					238,
					0.818,
					239,
					0.818,
					240,
					0.818,
					241,
					1.25,
					242,
					1.25,
					243,
					0.818,
					244,
					0.818,
					245,
					1.517,
					246,
					0.72,
					247,
					0.471,
					248,
					0.72,
					249,
					0.471,
					250,
					0.72,
					251,
					0.818,
					252,
					0.818,
					253,
					0.818,
					254,
					0.818,
					255,
					0.471,
					256,
					0.818,
					257,
					0.873,
					258,
					0.873,
					259,
					0.471,
					260,
					0.471,
					261,
					0.818,
					262,
					0.471,
					263,
					0.818,
					264,
					0.72,
					265,
					0.818,
					266,
					0.818,
					267,
					0.818,
					268,
					0.873,
					269,
					0.818,
					270,
					0.72,
					271,
					0.818,
					272,
					0.818,
					273,
					0.818,
					274,
					0.818,
					275,
					0.818,
					276,
					0.818,
					277,
					0.818,
					278,
					1.517,
					279,
					0.818,
					280,
					0.818,
					281,
					0.818,
					282,
					0.818,
					283,
					0.818,
					284,
					0.818,
					285,
					0.471,
					286,
					0.818,
					287,
					0.818,
					288,
					0.818,
					289,
					0.818,
					290,
					0.818,
					291,
					0.818,
					292,
					0.471,
					293,
					0.818,
					294,
					0.818,
					295,
					1.25,
					296,
					0.818,
					297,
					0.818,
					298,
					0.818,
					299,
					0.818,
					300,
					0.818,
					301,
					0.818,
					302,
					0.818,
					303,
					0.818,
					304,
					0.818,
					305,
					0.818,
					306,
					0.471,
					307,
					0.818,
					308,
					0.818,
					309,
					0.818,
					310,
					0.818,
					311,
					0.471,
					312,
					0.818,
					313,
					0.471
				]
			],
			[
				"title/quickstart.md",
				[
					110,
					1.22
				]
			],
			[
				"module/quickstart.md",
				[
					0,
					1.724,
					1,
					2.106
				]
			],
			[
				"group/quickstart.md",
				[]
			],
			[
				"body/quickstart.md",
				[
					1,
					0.845,
					2,
					0.152,
					3,
					0.381,
					4,
					0.381,
					5,
					0.113,
					6,
					0.113,
					8,
					0.113,
					11,
					0.113,
					12,
					0.183,
					26,
					0.381,
					35,
					0.113,
					36,
					0.381,
					39,
					0.381,
					42,
					0.381,
					43,
					0.381,
					44,
					0.381,
					45,
					0.381,
					46,
					0.381,
					47,
					0.693,
					49,
					0.381,
					52,
					0.381,
					53,
					0.741,
					56,
					0.227,
					58,
					0.381,
					59,
					0.381,
					63,
					0.142,
					65,
					0.113,
					68,
					0.58,
					69,
					0.513,
					70,
					0.381,
					71,
					0.513,
					73,
					0.381,
					74,
					0.58,
					80,
					0.381,
					81,
					0.171,
					82,
					0.513,
					84,
					0.513,
					86,
					0.113,
					87,
					0.113,
					88,
					0.381,
					89,
					0.513,
					90,
					0.381,
					91,
					0.58,
					92,
					0.58,
					93,
					0.381,
					95,
					0.152,
					99,
					0.152,
					100,
					0.381,
					103,
					0.381,
					104,
					0.513,
					109,
					0.381,
					110,
					0.113,
					111,
					0.381,
					112,
					0.513,
					114,
					0.381,
					115,
					0.381,
					116,
					0.381,
					117,
					0.513,
					121,
					0.58,
					124,
					0.381,
					125,
					0.513,
					126,
					0.513,
					127,
					0.191,
					128,
					1.206,
					129,
					0.381,
					131,
					0.381,
					132,
					0.381,
					133,
					0.381,
					134,
					0.513,
					135,
					0.997,
					142,
					0.741,
					143,
					0.741,
					144,
					0.381,
					183,
					0.741,
					191,
					0.997,
					195,
					0.741,
					197,
					0.741,
					208,
					0.741,
					211,
					0.741,
					218,
					0.997,
					221,
					0.997,
					233,
					0.741,
					246,
					0.741,
					247,
					0.997,
					248,
					0.997,
					249,
					0.741,
					250,
					1.127,
					255,
					0.741,
					257,
					0.741,
					258,
					0.741,
					259,
					0.741,
					260,
					1.127,
					262,
					0.741,
					264,
					0.741,
					268,
					0.741,
					270,
					0.997,
					285,
					0.741,
					292,
					0.741,
					306,
					0.741,
					311,
					0.997,
					313,
					0.741,
					314,
					1.287,
					315,
					1.287,
					316,
					1.732,
					317,
					1.287,
					318,
					1.287,
					319,
					1.287,
					320,
					1.287,
					321,
					2.095,
					322,
					1.732,
					323,
					1.287,
					324,
					1.732,
					325,
					1.732,
					326,
					1.287,
					327,
					1.287,
					328,
					1.287,
					329,
					1.287,
					330,
					1.287,
					331,
					1.287,
					332,
					1.287,
					333,
					1.287,
					334,
					1.287,
					335,
					1.287,
					336,
					1.287,
					337,
					1.287,
					338,
					1.287,
					339,
					1.732,
					340,
					1.732,
					341,
					1.732,
					342,
					1.287,
					343,
					1.287,
					344,
					1.732,
					345,
					1.287,
					346,
					1.287,
					347,
					1.732,
					348,
					1.287,
					349,
					1.732,
					350,
					1.287,
					351,
					1.287
				]
			]
		],
		"invertedIndex": [
			[
				"",
				{
					"_index": 56,
					"title": {},
					"module": {},
					"group": {},
					"body": {
						"README.md": {},
						"_cover.md": {},
						"how-it-works.md": {},
						"quickstart.md": {}
					}
				}
			],
			[
				"124",
				{
					"_index": 128,
					"title": {},
					"module": {},
					"group": {},
					"body": {
						"README.md": {},
						"quickstart.md": {}
					}
				}
			],
			[
				"1x1",
				{
					"_index": 89,
					"title": {},
					"module": {},
					"group": {},
					"body": {
						"README.md": {},
						"how-it-works.md": {},
						"quickstart.md": {}
					}
				}
			],
			[
				"accept",
				{
					"_index": 272,
					"title": {},
					"module": {},
					"group": {},
					"body": {
						"how-it-works.md": {}
					}
				}
			],
			[
				"access",
				{
					"_index": 284,
					"title": {},
					"module": {},
					"group": {},
					"body": {
						"how-it-works.md": {}
					}
				}
			],
			[
				"actual",
				{
					"_index": 264,
					"title": {},
					"module": {},
					"group": {},
					"body": {
						"how-it-works.md": {},
						"quickstart.md": {}
					}
				}
			],
			[
				"add",
				{
					"_index": 215,
					"title": {},
					"module": {},
					"group": {},
					"body": {
						"how-it-works.md": {}
					}
				}
			],
			[
				"addit",
				{
					"_index": 120,
					"title": {},
					"module": {},
					"group": {},
					"body": {
						"README.md": {}
					}
				}
			],
			[
				"addition",
				{
					"_index": 97,
					"title": {},
					"module": {},
					"group": {},
					"body": {
						"README.md": {},
						"how-it-works.md": {}
					}
				}
			],
			[
				"again",
				{
					"_index": 210,
					"title": {},
					"module": {},
					"group": {},
					"body": {
						"how-it-works.md": {}
					}
				}
			],
			[
				"against",
				{
					"_index": 164,
					"title": {},
					"module": {},
					"group": {},
					"body": {
						"how-it-works.md": {}
					}
				}
			],
			[
				"alreadi",
				{
					"_index": 80,
					"title": {},
					"module": {},
					"group": {},
					"body": {
						"README.md": {},
						"how-it-works.md": {},
						"quickstart.md": {}
					}
				}
			],
			[
				"alway",
				{
					"_index": 328,
					"title": {},
					"module": {},
					"group": {},
					"body": {
						"quickstart.md": {}
					}
				}
			],
			[
				"anyth",
				{
					"_index": 193,
					"title": {},
					"module": {},
					"group": {},
					"body": {
						"how-it-works.md": {}
					}
				}
			],
			[
				"anywher",
				{
					"_index": 72,
					"title": {},
					"module": {},
					"group": {},
					"body": {
						"README.md": {},
						"_cover.md": {},
						"how-it-works.md": {}
					}
				}
			],
			[
				"api",
				{
					"_index": 321,
					"title": {},
					"module": {},
					"group": {},
					"body": {
						"quickstart.md": {}
					}
				}
			],
			[
				"appli",
				{
					"_index": 274,
					"title": {},
					"module": {},
					"group": {},
					"body": {
						"how-it-works.md": {}
					}
				}
			],
			[
				"apt",
				{
					"_index": 24,
					"title": {},
					"module": {},
					"group": {},
					"body": {
						"README.md": {},
						"how-it-works.md": {}
					}
				}
			],
			[
				"architectur",
				{
					"_index": 139,
					"title": {},
					"module": {},
					"group": {},
					"body": {
						"README.md": {},
						"how-it-works.md": {}
					}
				}
			],
			[
				"argument",
				{
					"_index": 350,
					"title": {},
					"module": {},
					"group": {},
					"body": {
						"quickstart.md": {}
					}
				}
			],
			[
				"around",
				{
					"_index": 4,
					"title": {},
					"module": {},
					"group": {},
					"body": {
						"README.md": {},
						"_cover.md": {},
						"quickstart.md": {}
					}
				}
			],
			[
				"attach",
				{
					"_index": 243,
					"title": {},
					"module": {},
					"group": {},
					"body": {
						"how-it-works.md": {}
					}
				}
			],
			[
				"automat",
				{
					"_index": 276,
					"title": {},
					"module": {},
					"group": {},
					"body": {
						"how-it-works.md": {}
					}
				}
			],
			[
				"avail",
				{
					"_index": 322,
					"title": {},
					"module": {},
					"group": {},
					"body": {
						"quickstart.md": {}
					}
				}
			],
			[
				"back",
				{
					"_index": 218,
					"title": {},
					"module": {},
					"group": {},
					"body": {
						"how-it-works.md": {},
						"quickstart.md": {}
					}
				}
			],
			[
				"bad",
				{
					"_index": 163,
					"title": {},
					"module": {},
					"group": {},
					"body": {
						"how-it-works.md": {}
					}
				}
			],
			[
				"base",
				{
					"_index": 338,
					"title": {},
					"module": {},
					"group": {},
					"body": {
						"quickstart.md": {}
					}
				}
			],
			[
				"becom",
				{
					"_index": 332,
					"title": {},
					"module": {},
					"group": {},
					"body": {
						"quickstart.md": {}
					}
				}
			],
			[
				"befor",
				{
					"_index": 46,
					"title": {},
					"module": {},
					"group": {},
					"body": {
						"README.md": {},
						"how-it-works.md": {},
						"quickstart.md": {}
					}
				}
			],
			[
				"behavior",
				{
					"_index": 288,
					"title": {},
					"module": {},
					"group": {},
					"body": {
						"how-it-works.md": {}
					}
				}
			],
			[
				"binari",
				{
					"_index": 100,
					"title": {},
					"module": {},
					"group": {},
					"body": {
						"README.md": {},
						"how-it-works.md": {},
						"quickstart.md": {}
					}
				}
			],
			[
				"bind",
				{
					"_index": 127,
					"title": {},
					"module": {},
					"group": {},
					"body": {
						"README.md": {},
						"_cover.md": {},
						"how-it-works.md": {},
						"quickstart.md": {}
					}
				}
			],
			[
				"block",
				{
					"_index": 223,
					"title": {},
					"module": {},
					"group": {},
					"body": {
						"how-it-works.md": {}
					}
				}
			],
			[
				"boot",
				{
					"_index": 346,
					"title": {},
					"module": {},
					"group": {},
					"body": {
						"quickstart.md": {}
					}
				}
			],
			[
				"bootstrap",
				{
					"_index": 74,
					"title": {},
					"module": {},
					"group": {},
					"body": {
						"README.md": {},
						"how-it-works.md": {},
						"quickstart.md": {}
					}
				}
			],
			[
				"bootstrap'",
				{
					"_index": 240,
					"title": {},
					"module": {},
					"group": {},
					"body": {
						"how-it-works.md": {}
					}
				}
			],
			[
				"both",
				{
					"_index": 161,
					"title": {},
					"module": {},
					"group": {},
					"body": {
						"how-it-works.md": {}
					}
				}
			],
			[
				"buffer",
				{
					"_index": 125,
					"title": {},
					"module": {},
					"group": {},
					"body": {
						"README.md": {},
						"how-it-works.md": {},
						"quickstart.md": {}
					}
				}
			],
			[
				"build",
				{
					"_index": 35,
					"title": {},
					"module": {},
					"group": {},
					"body": {
						"README.md": {},
						"_cover.md": {},
						"how-it-works.md": {},
						"quickstart.md": {}
					}
				}
			],
			[
				"built",
				{
					"_index": 235,
					"title": {},
					"module": {},
					"group": {},
					"body": {
						"how-it-works.md": {}
					}
				}
			],
			[
				"bump",
				{
					"_index": 225,
					"title": {},
					"module": {},
					"group": {},
					"body": {
						"how-it-works.md": {}
					}
				}
			],
			[
				"bundl",
				{
					"_index": 111,
					"title": {},
					"module": {},
					"group": {},
					"body": {
						"README.md": {},
						"how-it-works.md": {},
						"quickstart.md": {}
					}
				}
			],
			[
				"bypass",
				{
					"_index": 7,
					"title": {},
					"module": {},
					"group": {},
					"body": {
						"README.md": {},
						"_cover.md": {},
						"how-it-works.md": {}
					}
				}
			],
			[
				"cach",
				{
					"_index": 282,
					"title": {},
					"module": {},
					"group": {},
					"body": {
						"how-it-works.md": {}
					}
				}
			],
			[
				"call",
				{
					"_index": 195,
					"title": {},
					"module": {},
					"group": {},
					"body": {
						"how-it-works.md": {},
						"quickstart.md": {}
					}
				}
			],
			[
				"callabl",
				{
					"_index": 334,
					"title": {},
					"module": {},
					"group": {},
					"body": {
						"quickstart.md": {}
					}
				}
			],
			[
				"carri",
				{
					"_index": 118,
					"title": {},
					"module": {},
					"group": {},
					"body": {
						"README.md": {},
						"how-it-works.md": {}
					}
				}
			],
			[
				"case",
				{
					"_index": 132,
					"title": {},
					"module": {},
					"group": {},
					"body": {
						"README.md": {},
						"how-it-works.md": {},
						"quickstart.md": {}
					}
				}
			],
			[
				"catch",
				{
					"_index": 131,
					"title": {},
					"module": {},
					"group": {},
					"body": {
						"README.md": {},
						"how-it-works.md": {},
						"quickstart.md": {}
					}
				}
			],
			[
				"chain",
				{
					"_index": 258,
					"title": {},
					"module": {},
					"group": {},
					"body": {
						"how-it-works.md": {},
						"quickstart.md": {}
					}
				}
			],
			[
				"chang",
				{
					"_index": 320,
					"title": {},
					"module": {},
					"group": {},
					"body": {
						"quickstart.md": {}
					}
				}
			],
			[
				"check",
				{
					"_index": 194,
					"title": {},
					"module": {},
					"group": {},
					"body": {
						"how-it-works.md": {}
					}
				}
			],
			[
				"child",
				{
					"_index": 58,
					"title": {},
					"module": {},
					"group": {},
					"body": {
						"README.md": {},
						"how-it-works.md": {},
						"quickstart.md": {}
					}
				}
			],
			[
				"child'",
				{
					"_index": 205,
					"title": {},
					"module": {},
					"group": {},
					"body": {
						"how-it-works.md": {}
					}
				}
			],
			[
				"ci",
				{
					"_index": 280,
					"title": {},
					"module": {},
					"group": {},
					"body": {
						"how-it-works.md": {}
					}
				}
			],
			[
				"classic",
				{
					"_index": 136,
					"title": {},
					"module": {},
					"group": {},
					"body": {
						"README.md": {},
						"how-it-works.md": {}
					}
				}
			],
			[
				"clean",
				{
					"_index": 50,
					"title": {},
					"module": {},
					"group": {},
					"body": {
						"README.md": {},
						"how-it-works.md": {}
					}
				}
			],
			[
				"cleanli",
				{
					"_index": 336,
					"title": {},
					"module": {},
					"group": {},
					"body": {
						"quickstart.md": {}
					}
				}
			],
			[
				"close",
				{
					"_index": 172,
					"title": {},
					"module": {},
					"group": {},
					"body": {
						"how-it-works.md": {}
					}
				}
			],
			[
				"code",
				{
					"_index": 318,
					"title": {},
					"module": {},
					"group": {},
					"body": {
						"quickstart.md": {}
					}
				}
			],
			[
				"compil",
				{
					"_index": 28,
					"title": {},
					"module": {},
					"group": {},
					"body": {
						"README.md": {},
						"how-it-works.md": {}
					}
				}
			],
			[
				"condit",
				{
					"_index": 335,
					"title": {},
					"module": {},
					"group": {},
					"body": {
						"quickstart.md": {}
					}
				}
			],
			[
				"confirm",
				{
					"_index": 311,
					"title": {},
					"module": {},
					"group": {},
					"body": {
						"how-it-works.md": {},
						"quickstart.md": {}
					}
				}
			],
			[
				"constructor",
				{
					"_index": 70,
					"title": {},
					"module": {},
					"group": {},
					"body": {
						"README.md": {},
						"how-it-works.md": {},
						"quickstart.md": {}
					}
				}
			],
			[
				"consum",
				{
					"_index": 60,
					"title": {},
					"module": {},
					"group": {},
					"body": {
						"README.md": {},
						"how-it-works.md": {}
					}
				}
			],
			[
				"control",
				{
					"_index": 116,
					"title": {},
					"module": {},
					"group": {},
					"body": {
						"README.md": {},
						"how-it-works.md": {},
						"quickstart.md": {}
					}
				}
			],
			[
				"conveni",
				{
					"_index": 310,
					"title": {},
					"module": {},
					"group": {},
					"body": {
						"how-it-works.md": {}
					}
				}
			],
			[
				"convers",
				{
					"_index": 147,
					"title": {},
					"module": {},
					"group": {},
					"body": {
						"README.md": {},
						"how-it-works.md": {}
					}
				}
			],
			[
				"copi",
				{
					"_index": 85,
					"title": {},
					"module": {},
					"group": {},
					"body": {
						"README.md": {},
						"_cover.md": {},
						"how-it-works.md": {}
					}
				}
			],
			[
				"cover",
				{
					"_index": 160,
					"title": {},
					"module": {},
					"group": {},
					"body": {
						"how-it-works.md": {}
					}
				}
			],
			[
				"crash",
				{
					"_index": 249,
					"title": {},
					"module": {},
					"group": {},
					"body": {
						"how-it-works.md": {},
						"quickstart.md": {}
					}
				}
			],
			[
				"custom",
				{
					"_index": 237,
					"title": {},
					"module": {},
					"group": {},
					"body": {
						"how-it-works.md": {}
					}
				}
			],
			[
				"decid",
				{
					"_index": 253,
					"title": {},
					"module": {},
					"group": {},
					"body": {
						"how-it-works.md": {}
					}
				}
			],
			[
				"decis",
				{
					"_index": 241,
					"title": {},
					"module": {},
					"group": {},
					"body": {
						"how-it-works.md": {}
					}
				}
			],
			[
				"default",
				{
					"_index": 68,
					"title": {},
					"module": {},
					"group": {},
					"body": {
						"README.md": {},
						"how-it-works.md": {},
						"quickstart.md": {}
					}
				}
			],
			[
				"depend",
				{
					"_index": 61,
					"title": {},
					"module": {},
					"group": {},
					"body": {
						"README.md": {},
						"how-it-works.md": {}
					}
				}
			],
			[
				"dependency'",
				{
					"_index": 171,
					"title": {},
					"module": {},
					"group": {},
					"body": {
						"how-it-works.md": {}
					}
				}
			],
			[
				"describ",
				{
					"_index": 289,
					"title": {},
					"module": {},
					"group": {},
					"body": {
						"how-it-works.md": {}
					}
				}
			],
			[
				"detect",
				{
					"_index": 11,
					"title": {},
					"module": {},
					"group": {},
					"body": {
						"README.md": {},
						"_cover.md": {},
						"how-it-works.md": {},
						"quickstart.md": {}
					}
				}
			],
			[
				"diagnos",
				{
					"_index": 162,
					"title": {},
					"module": {},
					"group": {},
					"body": {
						"how-it-works.md": {}
					}
				}
			],
			[
				"diagnost",
				{
					"_index": 86,
					"title": {},
					"module": {},
					"group": {},
					"body": {
						"README.md": {},
						"_cover.md": {},
						"how-it-works.md": {},
						"quickstart.md": {}
					}
				}
			],
			[
				"directli",
				{
					"_index": 312,
					"title": {},
					"module": {},
					"group": {},
					"body": {
						"how-it-works.md": {}
					}
				}
			],
			[
				"directori",
				{
					"_index": 197,
					"title": {},
					"module": {},
					"group": {},
					"body": {
						"how-it-works.md": {},
						"quickstart.md": {}
					}
				}
			],
			[
				"disk",
				{
					"_index": 129,
					"title": {},
					"module": {},
					"group": {},
					"body": {
						"README.md": {},
						"how-it-works.md": {},
						"quickstart.md": {}
					}
				}
			],
			[
				"divert",
				{
					"_index": 222,
					"title": {},
					"module": {},
					"group": {},
					"body": {
						"how-it-works.md": {}
					}
				}
			],
			[
				"do",
				{
					"_index": 192,
					"title": {},
					"module": {},
					"group": {},
					"body": {
						"how-it-works.md": {}
					}
				}
			],
			[
				"document",
				{
					"_index": 142,
					"title": {},
					"module": {},
					"group": {},
					"body": {
						"README.md": {},
						"quickstart.md": {}
					}
				}
			],
			[
				"drop",
				{
					"_index": 2,
					"title": {},
					"module": {},
					"group": {},
					"body": {
						"README.md": {},
						"_cover.md": {},
						"how-it-works.md": {},
						"quickstart.md": {}
					}
				}
			],
			[
				"dure",
				{
					"_index": 114,
					"title": {},
					"module": {},
					"group": {},
					"body": {
						"README.md": {},
						"how-it-works.md": {},
						"quickstart.md": {}
					}
				}
			],
			[
				"effect",
				{
					"_index": 275,
					"title": {},
					"module": {},
					"group": {},
					"body": {
						"how-it-works.md": {}
					}
				}
			],
			[
				"endpoint",
				{
					"_index": 148,
					"title": {},
					"module": {},
					"group": {},
					"body": {
						"README.md": {},
						"how-it-works.md": {}
					}
				}
			],
			[
				"entir",
				{
					"_index": 279,
					"title": {},
					"module": {},
					"group": {},
					"body": {
						"how-it-works.md": {}
					}
				}
			],
			[
				"entri",
				{
					"_index": 227,
					"title": {},
					"module": {},
					"group": {},
					"body": {
						"how-it-works.md": {}
					}
				}
			],
			[
				"environ",
				{
					"_index": 45,
					"title": {},
					"module": {},
					"group": {},
					"body": {
						"README.md": {},
						"how-it-works.md": {},
						"quickstart.md": {}
					}
				}
			],
			[
				"error",
				{
					"_index": 39,
					"title": {},
					"module": {},
					"group": {},
					"body": {
						"README.md": {},
						"how-it-works.md": {},
						"quickstart.md": {}
					}
				}
			],
			[
				"exactli",
				{
					"_index": 315,
					"title": {},
					"module": {},
					"group": {},
					"body": {
						"quickstart.md": {}
					}
				}
			],
			[
				"exampl",
				{
					"_index": 260,
					"title": {},
					"module": {},
					"group": {},
					"body": {
						"how-it-works.md": {},
						"quickstart.md": {}
					}
				}
			],
			[
				"exercis",
				{
					"_index": 126,
					"title": {},
					"module": {},
					"group": {},
					"body": {
						"README.md": {},
						"how-it-works.md": {},
						"quickstart.md": {}
					}
				}
			],
			[
				"exist",
				{
					"_index": 14,
					"title": {},
					"module": {},
					"group": {},
					"body": {
						"README.md": {},
						"how-it-works.md": {}
					}
				}
			],
			[
				"exit",
				{
					"_index": 184,
					"title": {},
					"module": {},
					"group": {},
					"body": {
						"how-it-works.md": {}
					}
				}
			],
			[
				"explain",
				{
					"_index": 305,
					"title": {},
					"module": {},
					"group": {},
					"body": {
						"how-it-works.md": {}
					}
				}
			],
			[
				"export",
				{
					"_index": 69,
					"title": {},
					"module": {},
					"group": {},
					"body": {
						"README.md": {},
						"how-it-works.md": {},
						"quickstart.md": {}
					}
				}
			],
			[
				"expos",
				{
					"_index": 40,
					"title": {},
					"module": {},
					"group": {},
					"body": {
						"README.md": {},
						"how-it-works.md": {}
					}
				}
			],
			[
				"extern",
				{
					"_index": 149,
					"title": {},
					"module": {},
					"group": {},
					"body": {
						"README.md": {},
						"how-it-works.md": {}
					}
				}
			],
			[
				"fail",
				{
					"_index": 37,
					"title": {},
					"module": {},
					"group": {},
					"body": {
						"README.md": {},
						"how-it-works.md": {}
					}
				}
			],
			[
				"failur",
				{
					"_index": 140,
					"title": {},
					"module": {},
					"group": {},
					"body": {
						"README.md": {},
						"how-it-works.md": {}
					}
				}
			],
			[
				"fall",
				{
					"_index": 217,
					"title": {},
					"module": {},
					"group": {},
					"body": {
						"how-it-works.md": {}
					}
				}
			],
			[
				"fallback",
				{
					"_index": 96,
					"title": {},
					"module": {},
					"group": {},
					"body": {
						"README.md": {},
						"how-it-works.md": {}
					}
				}
			],
			[
				"fastest",
				{
					"_index": 314,
					"title": {},
					"module": {},
					"group": {},
					"body": {
						"quickstart.md": {}
					}
				}
			],
			[
				"fatal",
				{
					"_index": 220,
					"title": {},
					"module": {},
					"group": {},
					"body": {
						"how-it-works.md": {}
					}
				}
			],
			[
				"featur",
				{
					"_index": 66,
					"title": {},
					"module": {},
					"group": {},
					"body": {
						"README.md": {}
					}
				}
			],
			[
				"fetch",
				{
					"_index": 115,
					"title": {},
					"module": {},
					"group": {},
					"body": {
						"README.md": {},
						"how-it-works.md": {},
						"quickstart.md": {}
					}
				}
			],
			[
				"filesystem",
				{
					"_index": 256,
					"title": {},
					"module": {},
					"group": {},
					"body": {
						"how-it-works.md": {}
					}
				}
			],
			[
				"final",
				{
					"_index": 304,
					"title": {},
					"module": {},
					"group": {},
					"body": {
						"how-it-works.md": {}
					}
				}
			],
			[
				"first",
				{
					"_index": 292,
					"title": {},
					"module": {},
					"group": {},
					"body": {
						"how-it-works.md": {},
						"quickstart.md": {}
					}
				}
			],
			[
				"flag",
				{
					"_index": 189,
					"title": {},
					"module": {},
					"group": {},
					"body": {
						"how-it-works.md": {}
					}
				}
			],
			[
				"forc",
				{
					"_index": 168,
					"title": {},
					"module": {},
					"group": {},
					"body": {
						"how-it-works.md": {}
					}
				}
			],
			[
				"found",
				{
					"_index": 233,
					"title": {},
					"module": {},
					"group": {},
					"body": {
						"how-it-works.md": {},
						"quickstart.md": {}
					}
				}
			],
			[
				"four",
				{
					"_index": 329,
					"title": {},
					"module": {},
					"group": {},
					"body": {
						"quickstart.md": {}
					}
				}
			],
			[
				"full",
				{
					"_index": 316,
					"title": {},
					"module": {},
					"group": {},
					"body": {
						"quickstart.md": {}
					}
				}
			],
			[
				"fulli",
				{
					"_index": 269,
					"title": {},
					"module": {},
					"group": {},
					"body": {
						"how-it-works.md": {}
					}
				}
			],
			[
				"function",
				{
					"_index": 247,
					"title": {},
					"module": {},
					"group": {},
					"body": {
						"how-it-works.md": {},
						"quickstart.md": {}
					}
				}
			],
			[
				"further",
				{
					"_index": 267,
					"title": {},
					"module": {},
					"group": {},
					"body": {
						"how-it-works.md": {}
					}
				}
			],
			[
				"gap",
				{
					"_index": 173,
					"title": {},
					"module": {},
					"group": {},
					"body": {
						"how-it-works.md": {}
					}
				}
			],
			[
				"get",
				{
					"_index": 238,
					"title": {},
					"module": {},
					"group": {},
					"body": {
						"how-it-works.md": {}
					}
				}
			],
			[
				"github",
				{
					"_index": 153,
					"title": {},
					"module": {},
					"group": {},
					"body": {
						"_cover.md": {}
					}
				}
			],
			[
				"global",
				{
					"_index": 9,
					"title": {},
					"module": {},
					"group": {},
					"body": {
						"README.md": {},
						"_cover.md": {}
					}
				}
			],
			[
				"goe",
				{
					"_index": 266,
					"title": {},
					"module": {},
					"group": {},
					"body": {
						"how-it-works.md": {}
					}
				}
			],
			[
				"happen",
				{
					"_index": 31,
					"title": {},
					"module": {},
					"group": {},
					"body": {
						"README.md": {}
					}
				}
			],
			[
				"helper",
				{
					"_index": 87,
					"title": {},
					"module": {},
					"group": {},
					"body": {
						"README.md": {},
						"_cover.md": {},
						"how-it-works.md": {},
						"quickstart.md": {}
					}
				}
			],
			[
				"here",
				{
					"_index": 219,
					"title": {},
					"module": {},
					"group": {},
					"body": {
						"how-it-works.md": {}
					}
				}
			],
			[
				"high",
				{
					"_index": 150,
					"title": {},
					"module": {},
					"group": {},
					"body": {
						"README.md": {}
					}
				}
			],
			[
				"higher",
				{
					"_index": 231,
					"title": {},
					"module": {},
					"group": {},
					"body": {
						"how-it-works.md": {}
					}
				}
			],
			[
				"homebrew",
				{
					"_index": 23,
					"title": {},
					"module": {},
					"group": {},
					"body": {
						"README.md": {},
						"how-it-works.md": {}
					}
				}
			],
			[
				"honor",
				{
					"_index": 188,
					"title": {},
					"module": {},
					"group": {},
					"body": {
						"how-it-works.md": {}
					}
				}
			],
			[
				"hook",
				{
					"_index": 177,
					"title": {},
					"module": {},
					"group": {},
					"body": {
						"how-it-works.md": {}
					}
				}
			],
			[
				"host",
				{
					"_index": 65,
					"title": {},
					"module": {},
					"group": {},
					"body": {
						"README.md": {},
						"_cover.md": {},
						"how-it-works.md": {},
						"quickstart.md": {}
					}
				}
			],
			[
				"http",
				{
					"_index": 309,
					"title": {},
					"module": {},
					"group": {},
					"body": {
						"how-it-works.md": {}
					}
				}
			],
			[
				"idempot",
				{
					"_index": 179,
					"title": {},
					"module": {},
					"group": {},
					"body": {
						"how-it-works.md": {}
					}
				}
			],
			[
				"imag",
				{
					"_index": 5,
					"title": {},
					"module": {},
					"group": {},
					"body": {
						"README.md": {},
						"_cover.md": {},
						"how-it-works.md": {},
						"quickstart.md": {}
					}
				}
			],
			[
				"immedi",
				{
					"_index": 185,
					"title": {},
					"module": {},
					"group": {},
					"body": {
						"how-it-works.md": {}
					}
				}
			],
			[
				"inject",
				{
					"_index": 57,
					"title": {},
					"module": {},
					"group": {},
					"body": {
						"README.md": {},
						"how-it-works.md": {}
					}
				}
			],
			[
				"insid",
				{
					"_index": 345,
					"title": {},
					"module": {},
					"group": {},
					"body": {
						"quickstart.md": {}
					}
				}
			],
			[
				"inspect",
				{
					"_index": 255,
					"title": {},
					"module": {},
					"group": {},
					"body": {
						"how-it-works.md": {},
						"quickstart.md": {}
					}
				}
			],
			[
				"instal",
				{
					"_index": 12,
					"title": {},
					"module": {},
					"group": {},
					"body": {
						"README.md": {},
						"_cover.md": {},
						"how-it-works.md": {},
						"quickstart.md": {}
					}
				}
			],
			[
				"instanti",
				{
					"_index": 123,
					"title": {},
					"module": {},
					"group": {},
					"body": {
						"README.md": {},
						"how-it-works.md": {}
					}
				}
			],
			[
				"instead",
				{
					"_index": 62,
					"title": {},
					"module": {},
					"group": {},
					"body": {
						"README.md": {},
						"how-it-works.md": {}
					}
				}
			],
			[
				"itself",
				{
					"_index": 71,
					"title": {},
					"module": {},
					"group": {},
					"body": {
						"README.md": {},
						"how-it-works.md": {},
						"quickstart.md": {}
					}
				}
			],
			[
				"key",
				{
					"_index": 221,
					"title": {},
					"module": {},
					"group": {},
					"body": {
						"how-it-works.md": {},
						"quickstart.md": {}
					}
				}
			],
			[
				"leav",
				{
					"_index": 199,
					"title": {},
					"module": {},
					"group": {},
					"body": {
						"how-it-works.md": {}
					}
				}
			],
			[
				"level",
				{
					"_index": 54,
					"title": {},
					"module": {},
					"group": {},
					"body": {
						"README.md": {},
						"how-it-works.md": {}
					}
				}
			],
			[
				"librari",
				{
					"_index": 6,
					"title": {},
					"module": {},
					"group": {},
					"body": {
						"README.md": {},
						"_cover.md": {},
						"how-it-works.md": {},
						"quickstart.md": {}
					}
				}
			],
			[
				"libvip",
				{
					"_index": 10,
					"title": {},
					"module": {},
					"group": {},
					"body": {
						"README.md": {},
						"_cover.md": {},
						"how-it-works.md": {}
					}
				}
			],
			[
				"lifecycl",
				{
					"_index": 48,
					"title": {},
					"module": {},
					"group": {},
					"body": {
						"README.md": {},
						"how-it-works.md": {}
					}
				}
			],
			[
				"line",
				{
					"_index": 102,
					"title": {},
					"module": {},
					"group": {},
					"body": {
						"README.md": {},
						"how-it-works.md": {}
					}
				}
			],
			[
				"listen",
				{
					"_index": 348,
					"title": {},
					"module": {},
					"group": {},
					"body": {
						"quickstart.md": {}
					}
				}
			],
			[
				"live",
				{
					"_index": 104,
					"title": {},
					"module": {},
					"group": {},
					"body": {
						"README.md": {},
						"how-it-works.md": {},
						"quickstart.md": {}
					}
				}
			],
			[
				"load",
				{
					"_index": 134,
					"title": {},
					"module": {},
					"group": {},
					"body": {
						"README.md": {},
						"how-it-works.md": {},
						"quickstart.md": {}
					}
				}
			],
			[
				"loader",
				{
					"_index": 216,
					"title": {},
					"module": {},
					"group": {},
					"body": {
						"how-it-works.md": {}
					}
				}
			],
			[
				"log",
				{
					"_index": 190,
					"title": {},
					"module": {},
					"group": {},
					"body": {
						"how-it-works.md": {}
					}
				}
			],
			[
				"long",
				{
					"_index": 326,
					"title": {},
					"module": {},
					"group": {},
					"body": {
						"quickstart.md": {}
					}
				}
			],
			[
				"look",
				{
					"_index": 259,
					"title": {},
					"module": {},
					"group": {},
					"body": {
						"how-it-works.md": {},
						"quickstart.md": {}
					}
				}
			],
			[
				"machin",
				{
					"_index": 30,
					"title": {},
					"module": {},
					"group": {},
					"body": {
						"README.md": {},
						"how-it-works.md": {}
					}
				}
			],
			[
				"make",
				{
					"_index": 201,
					"title": {},
					"module": {},
					"group": {},
					"body": {
						"how-it-works.md": {}
					}
				}
			],
			[
				"match",
				{
					"_index": 239,
					"title": {},
					"module": {},
					"group": {},
					"body": {
						"how-it-works.md": {}
					}
				}
			],
			[
				"mean",
				{
					"_index": 295,
					"title": {},
					"module": {},
					"group": {},
					"body": {
						"how-it-works.md": {}
					}
				}
			],
			[
				"mechan",
				{
					"_index": 317,
					"title": {},
					"module": {},
					"group": {},
					"body": {
						"quickstart.md": {}
					}
				}
			],
			[
				"mention",
				{
					"_index": 286,
					"title": {},
					"module": {},
					"group": {},
					"body": {
						"how-it-works.md": {}
					}
				}
			],
			[
				"merg",
				{
					"_index": 204,
					"title": {},
					"module": {},
					"group": {},
					"body": {
						"how-it-works.md": {}
					}
				}
			],
			[
				"messag",
				{
					"_index": 268,
					"title": {},
					"module": {},
					"group": {},
					"body": {
						"how-it-works.md": {},
						"quickstart.md": {}
					}
				}
			],
			[
				"misbehav",
				{
					"_index": 290,
					"title": {},
					"module": {},
					"group": {},
					"body": {
						"how-it-works.md": {}
					}
				}
			],
			[
				"mislead",
				{
					"_index": 38,
					"title": {},
					"module": {},
					"group": {},
					"body": {
						"README.md": {},
						"how-it-works.md": {}
					}
				}
			],
			[
				"ml",
				{
					"_index": 25,
					"title": {},
					"module": {},
					"group": {},
					"body": {
						"README.md": {},
						"how-it-works.md": {}
					}
				}
			],
			[
				"mode",
				{
					"_index": 141,
					"title": {},
					"module": {},
					"group": {},
					"body": {
						"README.md": {},
						"how-it-works.md": {}
					}
				}
			],
			[
				"modul",
				{
					"_index": 133,
					"title": {},
					"module": {},
					"group": {},
					"body": {
						"README.md": {},
						"how-it-works.md": {},
						"quickstart.md": {}
					}
				}
			],
			[
				"move",
				{
					"_index": 154,
					"title": {},
					"module": {},
					"group": {},
					"body": {
						"how-it-works.md": {}
					}
				}
			],
			[
				"nativ",
				{
					"_index": 99,
					"title": {},
					"module": {},
					"group": {},
					"body": {
						"README.md": {},
						"_cover.md": {},
						"how-it-works.md": {},
						"quickstart.md": {}
					}
				}
			],
			[
				"network",
				{
					"_index": 283,
					"title": {},
					"module": {},
					"group": {},
					"body": {
						"how-it-works.md": {}
					}
				}
			],
			[
				"never",
				{
					"_index": 75,
					"title": {},
					"module": {},
					"group": {},
					"body": {
						"README.md": {},
						"_cover.md": {},
						"how-it-works.md": {}
					}
				}
			],
			[
				"node",
				{
					"_index": 344,
					"title": {},
					"module": {},
					"group": {},
					"body": {
						"quickstart.md": {}
					}
				}
			],
			[
				"node'",
				{
					"_index": 228,
					"title": {},
					"module": {},
					"group": {},
					"body": {
						"how-it-works.md": {}
					}
				}
			],
			[
				"non",
				{
					"_index": 293,
					"title": {},
					"module": {},
					"group": {},
					"body": {
						"how-it-works.md": {}
					}
				}
			],
			[
				"note",
				{
					"_index": 285,
					"title": {},
					"module": {},
					"group": {},
					"body": {
						"how-it-works.md": {},
						"quickstart.md": {}
					}
				}
			],
			[
				"noth",
				{
					"_index": 331,
					"title": {},
					"module": {},
					"group": {},
					"body": {
						"quickstart.md": {}
					}
				}
			],
			[
				"null",
				{
					"_index": 294,
					"title": {},
					"module": {},
					"group": {},
					"body": {
						"how-it-works.md": {}
					}
				}
			],
			[
				"object",
				{
					"_index": 117,
					"title": {},
					"module": {},
					"group": {},
					"body": {
						"README.md": {},
						"how-it-works.md": {},
						"quickstart.md": {}
					}
				}
			],
			[
				"odd",
				{
					"_index": 138,
					"title": {},
					"module": {},
					"group": {},
					"body": {
						"README.md": {},
						"how-it-works.md": {}
					}
				}
			],
			[
				"on",
				{
					"_index": 16,
					"title": {},
					"module": {},
					"group": {},
					"body": {
						"README.md": {},
						"how-it-works.md": {}
					}
				}
			],
			[
				"onto",
				{
					"_index": 244,
					"title": {},
					"module": {},
					"group": {},
					"body": {
						"how-it-works.md": {}
					}
				}
			],
			[
				"oper",
				{
					"_index": 325,
					"title": {},
					"module": {},
					"group": {},
					"body": {
						"quickstart.md": {}
					}
				}
			],
			[
				"opt",
				{
					"_index": 41,
					"title": {},
					"module": {},
					"group": {},
					"body": {
						"README.md": {},
						"how-it-works.md": {}
					}
				}
			],
			[
				"option",
				{
					"_index": 94,
					"title": {},
					"module": {},
					"group": {},
					"body": {
						"README.md": {},
						"how-it-works.md": {}
					}
				}
			],
			[
				"orat",
				{
					"_index": 146,
					"title": {},
					"module": {},
					"group": {},
					"body": {
						"README.md": {},
						"how-it-works.md": {}
					}
				}
			],
			[
				"order",
				{
					"_index": 187,
					"title": {},
					"module": {},
					"group": {},
					"body": {
						"how-it-works.md": {}
					}
				}
			],
			[
				"otherwis",
				{
					"_index": 202,
					"title": {},
					"module": {},
					"group": {},
					"body": {
						"how-it-works.md": {}
					}
				}
			],
			[
				"out",
				{
					"_index": 42,
					"title": {},
					"module": {},
					"group": {},
					"body": {
						"README.md": {},
						"how-it-works.md": {},
						"quickstart.md": {}
					}
				}
			],
			[
				"output",
				{
					"_index": 206,
					"title": {},
					"module": {},
					"group": {},
					"body": {
						"how-it-works.md": {}
					}
				}
			],
			[
				"outward",
				{
					"_index": 291,
					"title": {},
					"module": {},
					"group": {},
					"body": {
						"how-it-works.md": {}
					}
				}
			],
			[
				"over",
				{
					"_index": 308,
					"title": {},
					"module": {},
					"group": {},
					"body": {
						"how-it-works.md": {}
					}
				}
			],
			[
				"overrid",
				{
					"_index": 351,
					"title": {},
					"module": {},
					"group": {},
					"body": {
						"quickstart.md": {}
					}
				}
			],
			[
				"own",
				{
					"_index": 174,
					"title": {},
					"module": {},
					"group": {},
					"body": {
						"how-it-works.md": {}
					}
				}
			],
			[
				"packag",
				{
					"_index": 113,
					"title": {},
					"module": {},
					"group": {},
					"body": {
						"README.md": {},
						"how-it-works.md": {}
					}
				}
			],
			[
				"package'",
				{
					"_index": 105,
					"title": {},
					"module": {},
					"group": {},
					"body": {
						"README.md": {}
					}
				}
			],
			[
				"page",
				{
					"_index": 159,
					"title": {},
					"module": {},
					"group": {},
					"body": {
						"how-it-works.md": {}
					}
				}
			],
			[
				"parent",
				{
					"_index": 198,
					"title": {},
					"module": {},
					"group": {},
					"body": {
						"how-it-works.md": {}
					}
				}
			],
			[
				"part",
				{
					"_index": 155,
					"title": {},
					"module": {},
					"group": {},
					"body": {
						"how-it-works.md": {}
					}
				}
			],
			[
				"pass",
				{
					"_index": 183,
					"title": {},
					"module": {},
					"group": {},
					"body": {
						"how-it-works.md": {},
						"quickstart.md": {}
					}
				}
			],
			[
				"passthrough",
				{
					"_index": 79,
					"title": {},
					"module": {},
					"group": {},
					"body": {
						"README.md": {},
						"_cover.md": {},
						"how-it-works.md": {}
					}
				}
			],
			[
				"path",
				{
					"_index": 36,
					"title": {},
					"module": {},
					"group": {},
					"body": {
						"README.md": {},
						"how-it-works.md": {},
						"quickstart.md": {}
					}
				}
			],
			[
				"pattern",
				{
					"_index": 252,
					"title": {},
					"module": {},
					"group": {},
					"body": {
						"how-it-works.md": {}
					}
				}
			],
			[
				"perform",
				{
					"_index": 151,
					"title": {},
					"module": {},
					"group": {},
					"body": {
						"README.md": {}
					}
				}
			],
			[
				"perhap",
				{
					"_index": 236,
					"title": {},
					"module": {},
					"group": {},
					"body": {
						"how-it-works.md": {}
					}
				}
			],
			[
				"pict",
				{
					"_index": 337,
					"title": {},
					"module": {},
					"group": {},
					"body": {
						"quickstart.md": {}
					}
				}
			],
			[
				"pin",
				{
					"_index": 52,
					"title": {},
					"module": {},
					"group": {},
					"body": {
						"README.md": {},
						"how-it-works.md": {},
						"quickstart.md": {}
					}
				}
			],
			[
				"pipelin",
				{
					"_index": 26,
					"title": {},
					"module": {},
					"group": {},
					"body": {
						"README.md": {},
						"how-it-works.md": {},
						"quickstart.md": {}
					}
				}
			],
			[
				"pixel",
				{
					"_index": 90,
					"title": {},
					"module": {},
					"group": {},
					"body": {
						"README.md": {},
						"how-it-works.md": {},
						"quickstart.md": {}
					}
				}
			],
			[
				"place",
				{
					"_index": 200,
					"title": {},
					"module": {},
					"group": {},
					"body": {
						"how-it-works.md": {}
					}
				}
			],
			[
				"platform",
				{
					"_index": 98,
					"title": {},
					"module": {},
					"group": {},
					"body": {
						"README.md": {},
						"how-it-works.md": {}
					}
				}
			],
			[
				"platform/arch",
				{
					"_index": 261,
					"title": {},
					"module": {},
					"group": {},
					"body": {
						"how-it-works.md": {}
					}
				}
			],
			[
				"playground",
				{
					"_index": 112,
					"title": {},
					"module": {},
					"group": {},
					"body": {
						"README.md": {},
						"how-it-works.md": {},
						"quickstart.md": {}
					}
				}
			],
			[
				"plu",
				{
					"_index": 342,
					"title": {},
					"module": {},
					"group": {},
					"body": {
						"quickstart.md": {}
					}
				}
			],
			[
				"point",
				{
					"_index": 178,
					"title": {},
					"module": {},
					"group": {},
					"body": {
						"how-it-works.md": {}
					}
				}
			],
			[
				"port",
				{
					"_index": 349,
					"title": {},
					"module": {},
					"group": {},
					"body": {
						"quickstart.md": {}
					}
				}
			],
			[
				"portabl",
				{
					"_index": 170,
					"title": {},
					"module": {},
					"group": {},
					"body": {
						"how-it-works.md": {}
					}
				}
			],
			[
				"power",
				{
					"_index": 77,
					"title": {},
					"module": {},
					"group": {},
					"body": {
						"README.md": {},
						"_cover.md": {},
						"how-it-works.md": {}
					}
				}
			],
			[
				"prebuilt",
				{
					"_index": 169,
					"title": {},
					"module": {},
					"group": {},
					"body": {
						"how-it-works.md": {}
					}
				}
			],
			[
				"prefer",
				{
					"_index": 234,
					"title": {},
					"module": {},
					"group": {},
					"body": {
						"how-it-works.md": {}
					}
				}
			],
			[
				"prefix",
				{
					"_index": 302,
					"title": {},
					"module": {},
					"group": {},
					"body": {
						"how-it-works.md": {}
					}
				}
			],
			[
				"presenc",
				{
					"_index": 20,
					"title": {},
					"module": {},
					"group": {},
					"body": {
						"README.md": {}
					}
				}
			],
			[
				"present",
				{
					"_index": 32,
					"title": {},
					"module": {},
					"group": {},
					"body": {
						"README.md": {},
						"_cover.md": {},
						"how-it-works.md": {}
					}
				}
			],
			[
				"prime",
				{
					"_index": 281,
					"title": {},
					"module": {},
					"group": {},
					"body": {
						"how-it-works.md": {}
					}
				}
			],
			[
				"problem",
				{
					"_index": 18,
					"title": {},
					"module": {},
					"group": {},
					"body": {
						"README.md": {},
						"how-it-works.md": {}
					}
				}
			],
			[
				"process",
				{
					"_index": 59,
					"title": {},
					"module": {},
					"group": {},
					"body": {
						"README.md": {},
						"how-it-works.md": {},
						"quickstart.md": {}
					}
				}
			],
			[
				"project",
				{
					"_index": 53,
					"title": {},
					"module": {},
					"group": {},
					"body": {
						"README.md": {},
						"quickstart.md": {}
					}
				}
			],
			[
				"prove",
				{
					"_index": 265,
					"title": {},
					"module": {},
					"group": {},
					"body": {
						"how-it-works.md": {}
					}
				}
			],
			[
				"purpos",
				{
					"_index": 122,
					"title": {},
					"module": {},
					"group": {},
					"body": {
						"README.md": {}
					}
				}
			],
			[
				"quick",
				{
					"_index": 107,
					"title": {},
					"module": {},
					"group": {},
					"body": {
						"README.md": {}
					}
				}
			],
			[
				"quickstart",
				{
					"_index": 110,
					"title": {
						"quickstart.md": {}
					},
					"module": {},
					"group": {},
					"body": {
						"README.md": {},
						"how-it-works.md": {},
						"quickstart.md": {}
					}
				}
			],
			[
				"ran",
				{
					"_index": 296,
					"title": {},
					"module": {},
					"group": {},
					"body": {
						"how-it-works.md": {}
					}
				}
			],
			[
				"raw",
				{
					"_index": 124,
					"title": {},
					"module": {},
					"group": {},
					"body": {
						"README.md": {},
						"how-it-works.md": {},
						"quickstart.md": {}
					}
				}
			],
			[
				"re",
				{
					"_index": 245,
					"title": {},
					"module": {},
					"group": {},
					"body": {
						"how-it-works.md": {}
					}
				}
			],
			[
				"read",
				{
					"_index": 278,
					"title": {},
					"module": {},
					"group": {},
					"body": {
						"how-it-works.md": {}
					}
				}
			],
			[
				"readm",
				{
					"_index": 287,
					"title": {},
					"module": {},
					"group": {},
					"body": {
						"how-it-works.md": {}
					}
				}
			],
			[
				"reason",
				{
					"_index": 34,
					"title": {},
					"module": {},
					"group": {},
					"body": {
						"README.md": {},
						"how-it-works.md": {}
					}
				}
			],
			[
				"refer",
				{
					"_index": 324,
					"title": {},
					"module": {},
					"group": {},
					"body": {
						"quickstart.md": {}
					}
				}
			],
			[
				"regardless",
				{
					"_index": 64,
					"title": {},
					"module": {},
					"group": {},
					"body": {
						"README.md": {}
					}
				}
			],
			[
				"relat",
				{
					"_index": 145,
					"title": {},
					"module": {},
					"group": {},
					"body": {
						"README.md": {},
						"how-it-works.md": {}
					}
				}
			],
			[
				"reli",
				{
					"_index": 313,
					"title": {},
					"module": {},
					"group": {},
					"body": {
						"how-it-works.md": {},
						"quickstart.md": {}
					}
				}
			],
			[
				"remain",
				{
					"_index": 333,
					"title": {},
					"module": {},
					"group": {},
					"body": {
						"quickstart.md": {}
					}
				}
			],
			[
				"replac",
				{
					"_index": 67,
					"title": {},
					"module": {},
					"group": {},
					"body": {
						"README.md": {},
						"_cover.md": {}
					}
				}
			],
			[
				"report",
				{
					"_index": 93,
					"title": {},
					"module": {},
					"group": {},
					"body": {
						"README.md": {},
						"how-it-works.md": {},
						"quickstart.md": {}
					}
				}
			],
			[
				"reproduc",
				{
					"_index": 307,
					"title": {},
					"module": {},
					"group": {},
					"body": {
						"how-it-works.md": {}
					}
				}
			],
			[
				"request",
				{
					"_index": 224,
					"title": {},
					"module": {},
					"group": {},
					"body": {
						"how-it-works.md": {}
					}
				}
			],
			[
				"requir",
				{
					"_index": 250,
					"title": {},
					"module": {},
					"group": {},
					"body": {
						"how-it-works.md": {},
						"quickstart.md": {}
					}
				}
			],
			[
				"resolut",
				{
					"_index": 130,
					"title": {},
					"module": {},
					"group": {},
					"body": {
						"README.md": {},
						"how-it-works.md": {}
					}
				}
			],
			[
				"resolv",
				{
					"_index": 81,
					"title": {},
					"module": {},
					"group": {},
					"body": {
						"README.md": {},
						"_cover.md": {},
						"how-it-works.md": {},
						"quickstart.md": {}
					}
				}
			],
			[
				"resolver'",
				{
					"_index": 297,
					"title": {},
					"module": {},
					"group": {},
					"body": {
						"how-it-works.md": {}
					}
				}
			],
			[
				"rest",
				{
					"_index": 323,
					"title": {},
					"module": {},
					"group": {},
					"body": {
						"quickstart.md": {}
					}
				}
			],
			[
				"retold",
				{
					"_index": 0,
					"title": {
						"README.md": {},
						"_cover.md": {}
					},
					"module": {
						"README.md": {},
						"_cover.md": {},
						"how-it-works.md": {},
						"quickstart.md": {}
					},
					"group": {},
					"body": {
						"README.md": {},
						"_cover.md": {}
					}
				}
			],
			[
				"return",
				{
					"_index": 121,
					"title": {},
					"module": {},
					"group": {},
					"body": {
						"README.md": {},
						"how-it-works.md": {},
						"quickstart.md": {}
					}
				}
			],
			[
				"right",
				{
					"_index": 156,
					"title": {},
					"module": {},
					"group": {},
					"body": {
						"how-it-works.md": {}
					}
				}
			],
			[
				"root",
				{
					"_index": 306,
					"title": {},
					"module": {},
					"group": {},
					"body": {
						"how-it-works.md": {},
						"quickstart.md": {}
					}
				}
			],
			[
				"run",
				{
					"_index": 47,
					"title": {},
					"module": {},
					"group": {},
					"body": {
						"README.md": {},
						"how-it-works.md": {},
						"quickstart.md": {}
					}
				}
			],
			[
				"runtim",
				{
					"_index": 83,
					"title": {},
					"module": {},
					"group": {},
					"body": {
						"README.md": {},
						"how-it-works.md": {}
					}
				}
			],
			[
				"s",
				{
					"_index": 196,
					"title": {},
					"module": {},
					"group": {},
					"body": {
						"how-it-works.md": {}
					}
				}
			],
			[
				"safe",
				{
					"_index": 181,
					"title": {},
					"module": {},
					"group": {},
					"body": {
						"how-it-works.md": {}
					}
				}
			],
			[
				"same",
				{
					"_index": 73,
					"title": {},
					"module": {},
					"group": {},
					"body": {
						"README.md": {},
						"how-it-works.md": {},
						"quickstart.md": {}
					}
				}
			],
			[
				"script",
				{
					"_index": 49,
					"title": {},
					"module": {},
					"group": {},
					"body": {
						"README.md": {},
						"how-it-works.md": {},
						"quickstart.md": {}
					}
				}
			],
			[
				"second",
				{
					"_index": 182,
					"title": {},
					"module": {},
					"group": {},
					"body": {
						"how-it-works.md": {}
					}
				}
			],
			[
				"see",
				{
					"_index": 109,
					"title": {},
					"module": {},
					"group": {},
					"body": {
						"README.md": {},
						"how-it-works.md": {},
						"quickstart.md": {}
					}
				}
			],
			[
				"serv",
				{
					"_index": 339,
					"title": {},
					"module": {},
					"group": {},
					"body": {
						"quickstart.md": {}
					}
				}
			],
			[
				"server",
				{
					"_index": 347,
					"title": {},
					"module": {},
					"group": {},
					"body": {
						"quickstart.md": {}
					}
				}
			],
			[
				"servic",
				{
					"_index": 270,
					"title": {},
					"module": {},
					"group": {},
					"body": {
						"how-it-works.md": {},
						"quickstart.md": {}
					}
				}
			],
			[
				"set",
				{
					"_index": 44,
					"title": {},
					"module": {},
					"group": {},
					"body": {
						"README.md": {},
						"how-it-works.md": {},
						"quickstart.md": {}
					}
				}
			],
			[
				"shape",
				{
					"_index": 327,
					"title": {},
					"module": {},
					"group": {},
					"body": {
						"quickstart.md": {}
					}
				}
			],
			[
				"sharp",
				{
					"_index": 1,
					"title": {
						"README.md": {},
						"_cover.md": {}
					},
					"module": {
						"README.md": {},
						"_cover.md": {},
						"how-it-works.md": {},
						"quickstart.md": {}
					},
					"group": {},
					"body": {
						"README.md": {},
						"_cover.md": {},
						"how-it-works.md": {},
						"quickstart.md": {}
					}
				}
			],
			[
				"sharp'",
				{
					"_index": 8,
					"title": {},
					"module": {},
					"group": {},
					"body": {
						"README.md": {},
						"_cover.md": {},
						"how-it-works.md": {},
						"quickstart.md": {}
					}
				}
			],
			[
				"shell",
				{
					"_index": 208,
					"title": {},
					"module": {},
					"group": {},
					"body": {
						"how-it-works.md": {},
						"quickstart.md": {}
					}
				}
			],
			[
				"ship",
				{
					"_index": 167,
					"title": {},
					"module": {},
					"group": {},
					"body": {
						"how-it-works.md": {}
					}
				}
			],
			[
				"sibl",
				{
					"_index": 263,
					"title": {},
					"module": {},
					"group": {},
					"body": {
						"how-it-works.md": {}
					}
				}
			],
			[
				"side",
				{
					"_index": 251,
					"title": {},
					"module": {},
					"group": {},
					"body": {
						"how-it-works.md": {}
					}
				}
			],
			[
				"sign",
				{
					"_index": 301,
					"title": {},
					"module": {},
					"group": {},
					"body": {
						"how-it-works.md": {}
					}
				}
			],
			[
				"signal",
				{
					"_index": 27,
					"title": {},
					"module": {},
					"group": {},
					"body": {
						"README.md": {},
						"how-it-works.md": {}
					}
				}
			],
			[
				"singl",
				{
					"_index": 101,
					"title": {},
					"module": {},
					"group": {},
					"body": {
						"README.md": {},
						"how-it-works.md": {}
					}
				}
			],
			[
				"skip",
				{
					"_index": 82,
					"title": {},
					"module": {},
					"group": {},
					"body": {
						"README.md": {},
						"how-it-works.md": {},
						"quickstart.md": {}
					}
				}
			],
			[
				"small",
				{
					"_index": 343,
					"title": {},
					"module": {},
					"group": {},
					"body": {
						"quickstart.md": {}
					}
				}
			],
			[
				"smoke",
				{
					"_index": 91,
					"title": {},
					"module": {},
					"group": {},
					"body": {
						"README.md": {},
						"how-it-works.md": {},
						"quickstart.md": {}
					}
				}
			],
			[
				"solv",
				{
					"_index": 15,
					"title": {},
					"module": {},
					"group": {},
					"body": {
						"README.md": {}
					}
				}
			],
			[
				"someth",
				{
					"_index": 212,
					"title": {},
					"module": {},
					"group": {},
					"body": {
						"how-it-works.md": {}
					}
				}
			],
			[
				"sourc",
				{
					"_index": 29,
					"title": {},
					"module": {},
					"group": {},
					"body": {
						"README.md": {},
						"_cover.md": {},
						"how-it-works.md": {}
					}
				}
			],
			[
				"spawn",
				{
					"_index": 175,
					"title": {},
					"module": {},
					"group": {},
					"body": {
						"how-it-works.md": {}
					}
				}
			],
			[
				"spec",
				{
					"_index": 203,
					"title": {},
					"module": {},
					"group": {},
					"body": {
						"how-it-works.md": {}
					}
				}
			],
			[
				"specif",
				{
					"_index": 17,
					"title": {},
					"module": {},
					"group": {},
					"body": {
						"README.md": {}
					}
				}
			],
			[
				"stand",
				{
					"_index": 246,
					"title": {},
					"module": {},
					"group": {},
					"body": {
						"how-it-works.md": {},
						"quickstart.md": {}
					}
				}
			],
			[
				"standard",
				{
					"_index": 229,
					"title": {},
					"module": {},
					"group": {},
					"body": {
						"how-it-works.md": {}
					}
				}
			],
			[
				"start",
				{
					"_index": 108,
					"title": {},
					"module": {},
					"group": {},
					"body": {
						"README.md": {},
						"_cover.md": {},
						"how-it-works.md": {}
					}
				}
			],
			[
				"startup",
				{
					"_index": 271,
					"title": {},
					"module": {},
					"group": {},
					"body": {
						"how-it-works.md": {}
					}
				}
			],
			[
				"static",
				{
					"_index": 340,
					"title": {},
					"module": {},
					"group": {},
					"body": {
						"quickstart.md": {}
					}
				}
			],
			[
				"step",
				{
					"_index": 186,
					"title": {},
					"module": {},
					"group": {},
					"body": {
						"how-it-works.md": {}
					}
				}
			],
			[
				"still",
				{
					"_index": 211,
					"title": {},
					"module": {},
					"group": {},
					"body": {
						"how-it-works.md": {},
						"quickstart.md": {}
					}
				}
			],
			[
				"string",
				{
					"_index": 262,
					"title": {},
					"module": {},
					"group": {},
					"body": {
						"how-it-works.md": {},
						"quickstart.md": {}
					}
				}
			],
			[
				"succe",
				{
					"_index": 242,
					"title": {},
					"module": {},
					"group": {},
					"body": {
						"how-it-works.md": {}
					}
				}
			],
			[
				"surfac",
				{
					"_index": 298,
					"title": {},
					"module": {},
					"group": {},
					"body": {
						"how-it-works.md": {}
					}
				}
			],
			[
				"switch",
				{
					"_index": 319,
					"title": {},
					"module": {},
					"group": {},
					"body": {
						"quickstart.md": {}
					}
				}
			],
			[
				"synchron",
				{
					"_index": 88,
					"title": {},
					"module": {},
					"group": {},
					"body": {
						"README.md": {},
						"how-it-works.md": {},
						"quickstart.md": {}
					}
				}
			],
			[
				"synolog",
				{
					"_index": 137,
					"title": {},
					"module": {},
					"group": {},
					"body": {
						"README.md": {},
						"how-it-works.md": {}
					}
				}
			],
			[
				"system",
				{
					"_index": 21,
					"title": {},
					"module": {},
					"group": {},
					"body": {
						"README.md": {},
						"how-it-works.md": {}
					}
				}
			],
			[
				"taken",
				{
					"_index": 165,
					"title": {},
					"module": {},
					"group": {},
					"body": {
						"how-it-works.md": {}
					}
				}
			],
			[
				"tell",
				{
					"_index": 299,
					"title": {},
					"module": {},
					"group": {},
					"body": {
						"how-it-works.md": {}
					}
				}
			],
			[
				"test",
				{
					"_index": 92,
					"title": {},
					"module": {},
					"group": {},
					"body": {
						"README.md": {},
						"how-it-works.md": {},
						"quickstart.md": {}
					}
				}
			],
			[
				"through",
				{
					"_index": 55,
					"title": {},
					"module": {},
					"group": {},
					"body": {
						"README.md": {},
						"how-it-works.md": {}
					}
				}
			],
			[
				"throw",
				{
					"_index": 248,
					"title": {},
					"module": {},
					"group": {},
					"body": {
						"how-it-works.md": {},
						"quickstart.md": {}
					}
				}
			],
			[
				"time",
				{
					"_index": 13,
					"title": {},
					"module": {},
					"group": {},
					"body": {
						"README.md": {},
						"_cover.md": {},
						"how-it-works.md": {}
					}
				}
			],
			[
				"traffic",
				{
					"_index": 273,
					"title": {},
					"module": {},
					"group": {},
					"body": {
						"how-it-works.md": {}
					}
				}
			],
			[
				"treat",
				{
					"_index": 19,
					"title": {},
					"module": {},
					"group": {},
					"body": {
						"README.md": {},
						"how-it-works.md": {}
					}
				}
			],
			[
				"tree",
				{
					"_index": 232,
					"title": {},
					"module": {},
					"group": {},
					"body": {
						"how-it-works.md": {}
					}
				}
			],
			[
				"trigger",
				{
					"_index": 76,
					"title": {},
					"module": {},
					"group": {},
					"body": {
						"README.md": {},
						"_cover.md": {}
					}
				}
			],
			[
				"twice",
				{
					"_index": 180,
					"title": {},
					"module": {},
					"group": {},
					"body": {
						"how-it-works.md": {}
					}
				}
			],
			[
				"two",
				{
					"_index": 119,
					"title": {},
					"module": {},
					"group": {},
					"body": {
						"README.md": {},
						"how-it-works.md": {}
					}
				}
			],
			[
				"type",
				{
					"_index": 330,
					"title": {},
					"module": {},
					"group": {},
					"body": {
						"quickstart.md": {}
					}
				}
			],
			[
				"ui",
				{
					"_index": 341,
					"title": {},
					"module": {},
					"group": {},
					"body": {
						"quickstart.md": {}
					}
				}
			],
			[
				"under",
				{
					"_index": 106,
					"title": {},
					"module": {},
					"group": {},
					"body": {
						"README.md": {},
						"how-it-works.md": {}
					}
				}
			],
			[
				"underli",
				{
					"_index": 135,
					"title": {},
					"module": {},
					"group": {},
					"body": {
						"README.md": {},
						"quickstart.md": {}
					}
				}
			],
			[
				"unintention",
				{
					"_index": 166,
					"title": {},
					"module": {},
					"group": {},
					"body": {
						"how-it-works.md": {}
					}
				}
			],
			[
				"unrel",
				{
					"_index": 33,
					"title": {},
					"module": {},
					"group": {},
					"body": {
						"README.md": {},
						"how-it-works.md": {}
					}
				}
			],
			[
				"up",
				{
					"_index": 257,
					"title": {},
					"module": {},
					"group": {},
					"body": {
						"how-it-works.md": {},
						"quickstart.md": {}
					}
				}
			],
			[
				"upgrad",
				{
					"_index": 226,
					"title": {},
					"module": {},
					"group": {},
					"body": {
						"how-it-works.md": {}
					}
				}
			],
			[
				"upward",
				{
					"_index": 230,
					"title": {},
					"module": {},
					"group": {},
					"body": {
						"how-it-works.md": {}
					}
				}
			],
			[
				"us",
				{
					"_index": 84,
					"title": {},
					"module": {},
					"group": {},
					"body": {
						"README.md": {},
						"how-it-works.md": {},
						"quickstart.md": {}
					}
				}
			],
			[
				"usag",
				{
					"_index": 143,
					"title": {},
					"module": {},
					"group": {},
					"body": {
						"README.md": {},
						"quickstart.md": {}
					}
				}
			],
			[
				"user",
				{
					"_index": 78,
					"title": {},
					"module": {},
					"group": {},
					"body": {
						"README.md": {},
						"_cover.md": {},
						"how-it-works.md": {}
					}
				}
			],
			[
				"usual",
				{
					"_index": 300,
					"title": {},
					"module": {},
					"group": {},
					"body": {
						"how-it-works.md": {}
					}
				}
			],
			[
				"variabl",
				{
					"_index": 43,
					"title": {},
					"module": {},
					"group": {},
					"body": {
						"README.md": {},
						"how-it-works.md": {},
						"quickstart.md": {}
					}
				}
			],
			[
				"verifi",
				{
					"_index": 209,
					"title": {},
					"module": {},
					"group": {},
					"body": {
						"how-it-works.md": {}
					}
				}
			],
			[
				"version",
				{
					"_index": 103,
					"title": {},
					"module": {},
					"group": {},
					"body": {
						"README.md": {},
						"how-it-works.md": {},
						"quickstart.md": {}
					}
				}
			],
			[
				"via",
				{
					"_index": 22,
					"title": {},
					"module": {},
					"group": {},
					"body": {
						"README.md": {}
					}
				}
			],
			[
				"visibl",
				{
					"_index": 207,
					"title": {},
					"module": {},
					"group": {},
					"body": {
						"how-it-works.md": {}
					}
				}
			],
			[
				"vs",
				{
					"_index": 254,
					"title": {},
					"module": {},
					"group": {},
					"body": {
						"how-it-works.md": {}
					}
				}
			],
			[
				"walk",
				{
					"_index": 144,
					"title": {},
					"module": {},
					"group": {},
					"body": {
						"README.md": {},
						"how-it-works.md": {},
						"quickstart.md": {}
					}
				}
			],
			[
				"wasm",
				{
					"_index": 95,
					"title": {},
					"module": {},
					"group": {},
					"body": {
						"README.md": {},
						"_cover.md": {},
						"how-it-works.md": {},
						"quickstart.md": {}
					}
				}
			],
			[
				"way",
				{
					"_index": 51,
					"title": {},
					"module": {},
					"group": {},
					"body": {
						"README.md": {},
						"how-it-works.md": {}
					}
				}
			],
			[
				"went",
				{
					"_index": 213,
					"title": {},
					"module": {},
					"group": {},
					"body": {
						"how-it-works.md": {}
					}
				}
			],
			[
				"whether",
				{
					"_index": 303,
					"title": {},
					"module": {},
					"group": {},
					"body": {
						"how-it-works.md": {}
					}
				}
			],
			[
				"whichev",
				{
					"_index": 157,
					"title": {},
					"module": {},
					"group": {},
					"body": {
						"how-it-works.md": {}
					}
				}
			],
			[
				"win",
				{
					"_index": 158,
					"title": {},
					"module": {},
					"group": {},
					"body": {
						"how-it-works.md": {}
					}
				}
			],
			[
				"wire",
				{
					"_index": 176,
					"title": {},
					"module": {},
					"group": {},
					"body": {
						"how-it-works.md": {}
					}
				}
			],
			[
				"without",
				{
					"_index": 191,
					"title": {},
					"module": {},
					"group": {},
					"body": {
						"how-it-works.md": {},
						"quickstart.md": {}
					}
				}
			],
			[
				"work",
				{
					"_index": 63,
					"title": {
						"how-it-works.md": {}
					},
					"module": {},
					"group": {},
					"body": {
						"README.md": {},
						"_cover.md": {},
						"how-it-works.md": {},
						"quickstart.md": {}
					}
				}
			],
			[
				"wrap",
				{
					"_index": 152,
					"title": {},
					"module": {},
					"group": {},
					"body": {
						"README.md": {}
					}
				}
			],
			[
				"wrapper",
				{
					"_index": 3,
					"title": {},
					"module": {},
					"group": {},
					"body": {
						"README.md": {},
						"_cover.md": {},
						"quickstart.md": {}
					}
				}
			],
			[
				"wrong",
				{
					"_index": 214,
					"title": {},
					"module": {},
					"group": {},
					"body": {
						"how-it-works.md": {}
					}
				}
			],
			[
				"yourself",
				{
					"_index": 277,
					"title": {},
					"module": {},
					"group": {},
					"body": {
						"how-it-works.md": {}
					}
				}
			]
		],
		"pipeline": [
			"stemmer"
		]
	},
	"Documents": {
		"README.md": {
			"Title": "retold-sharp",
			"Module": "retold-sharp",
			"Group": "",
			"DocPath": "README.md"
		},
		"_cover.md": {
			"Title": "retold-sharp",
			"Module": "retold-sharp",
			"Group": "",
			"DocPath": "_cover.md"
		},
		"how-it-works.md": {
			"Title": "How It Works",
			"Module": "retold-sharp",
			"Group": "",
			"DocPath": "how-it-works.md"
		},
		"quickstart.md": {
			"Title": "Quickstart",
			"Module": "retold-sharp",
			"Group": "",
			"DocPath": "quickstart.md"
		}
	}
}